deeplexer/__init__.py
deeplexer/deeplexer.py
deeplexer-0.0.4.dist-info/LICENSE
deeplexer-0.0.4.dist-info/METADATA
deeplexer-0.0.4.dist-info/WHEEL
deeplexer-0.0.4.dist-info/top_level.txt
deeplexer-0.0.4.dist-info/RECORD
