Metadata-Version: 2.1
Name: deeplexer
Version: 0.0.4
Summary: Free DeepL Pro even Quota Exceeded
Home-page: https://github.com/OrigamiDream/deeplexer.git
Author: OrigamiDream
Author-email: hello@origamidream.me
License: MIT
Keywords: machine translation,translate,translation,deepl,deeplx
Platform: any
Classifier: Development Status :: 4 - Beta
Classifier: Intended Audience :: Developers
Classifier: Environment :: Web Environment
Classifier: License :: OSI Approved :: MIT License
Classifier: Operating System :: OS Independent
Classifier: Programming Language :: Python :: 3.6
Classifier: Programming Language :: Python :: 3.7
Classifier: Programming Language :: Python :: 3.8
Classifier: Programming Language :: Python :: 3.9
Classifier: Programming Language :: Python :: 3.10
Classifier: Topic :: Internet :: WWW/HTTP :: Dynamic Content
Classifier: Topic :: Software Development :: Libraries :: Python Modules
Requires-Python: >=3.10
License-File: LICENSE
Requires-Dist: aiohttp >=3.9.5
Requires-Dist: brotli >=1.1.0
Requires-Dist: playwright >=1.44.0
